adjacent/__init__.py
adjacent/client.py
adjacent/context_processors.py
adjacent/utils.py
adjacent-1.1.0.dist-info/METADATA
adjacent-1.1.0.dist-info/RECORD
adjacent-1.1.0.dist-info/WHEEL
adjacent-1.1.0.dist-info/top_level.txt
