Metadata-Version: 2.1
Name: adjacent
Version: 1.1.0
Summary: Centrifuge integration with Django framework
Home-page: https://github.com/centrifugal/adjacent
Author: Alexandr Emelin
Author-email: frvzmb@gmail.com
License: MIT
Download-URL: https://github.com/centrifugal/adjacent
Platform: UNKNOWN
Classifier: Development Status :: 3 - Alpha
Classifier: Programming Language :: Python
Classifier: Programming Language :: Python :: 2.6
Classifier: Programming Language :: Python :: 2.7
Classifier: Programming Language :: Python :: 3.3
Classifier: Programming Language :: Python :: 3.4
Classifier: Programming Language :: Python :: 3.5
Classifier: Programming Language :: Python :: 3.6
Classifier: Programming Language :: Python :: 3.7
Classifier: Intended Audience :: Developers
Classifier: License :: OSI Approved :: MIT License
Classifier: Topic :: Internet :: WWW/HTTP
Classifier: Topic :: Software Development
Classifier: Topic :: Utilities
Requires-Dist: cent (>=1.0.0)
